setup.py
DataAnalysis/Home.py
DataAnalysis/__init__.py
DataAnalysis/app.py
DataAnalysis/common/__init__.py
DataAnalysis/common/database.py
DataAnalysis/common/parser.py
DataAnalysis/common/utils.py
DataAnalysis/models/__init__.py
DataAnalysis/models/data_models.py
DataAnalysis/pages/1_👤_用户行为分析.py
DataAnalysis/pages/2_🔍_内容搜索分析.py
DataAnalysis/pages/3_💰_销售转化分析.py
DataAnalysis/pages/__init__.py
DataAnalysis/services/__init__.py
DataAnalysis/services/behavior.py
DataAnalysis/services/sales.py
DataAnalysis/services/search.py
data_ann.egg-info/PKG-INFO
data_ann.egg-info/SOURCES.txt
data_ann.egg-info/dependency_links.txt
data_ann.egg-info/top_level.txt