Metadata-Version: 2.2
Name: data_ann
Version: 0.0.3
Summary: tools
Author: DYZ
Author-email: duyuchau@gmail.com
Maintainer: DYZ
Maintainer-email: duyuchau@gmail.com
License: MIT
Platform: all
Dynamic: author
Dynamic: author-email
Dynamic: description
Dynamic: description-content-type
Dynamic: license
Dynamic: maintainer
Dynamic: maintainer-email
Dynamic: platform
Dynamic: summary
